README.rst
setup.py
pyramid_flash_message/__init__.py
pyramid_flash_message/decorated.py
pyramid_flash_message/flash_message_panel.jinja2
pyramid_flash_message/flash_message_view.jinja2
pyramid_flash_message/message.py
pyramid_flash_message.egg-info/PKG-INFO
pyramid_flash_message.egg-info/SOURCES.txt
pyramid_flash_message.egg-info/dependency_links.txt
pyramid_flash_message.egg-info/not-zip-safe
pyramid_flash_message.egg-info/requires.txt
pyramid_flash_message.egg-info/top_level.txt