Metadata-Version: 1.1
Name: pyramid-flash-message
Version: 0.1.9
Summary: Small tool to add and show flash messages
Home-page: https://github.com/sahama/pyramid_flash_message
Author: Sayyid Hamid Mahdavi
Author-email: sayyid.hamid.mahdavi@gmail.com
License: UNKNOWN
Keywords: web wsgi bfg pylons pyramid flash message
Platform: UNKNOWN
Classifier: Programming Language :: Python
Classifier: Framework :: Pyramid
Classifier: Topic :: Internet :: WWW/HTTP
Classifier: Topic :: Internet :: WWW/HTTP :: WSGI :: Application
